activity_log/__init__.py
activity_log/admin.py
activity_log/conf.py
activity_log/middleware.py
activity_log/models.py
activity_log/router.py
activity_log/migrations/0001_initial.py
activity_log/migrations/__init__.py
django_activity_log-2.0.3.dist-info/LICENSE
django_activity_log-2.0.3.dist-info/METADATA
django_activity_log-2.0.3.dist-info/WHEEL
django_activity_log-2.0.3.dist-info/top_level.txt
django_activity_log-2.0.3.dist-info/RECORD
