Metadata-Version: 2.1
Name: django-activity-log
Version: 2.0.3
Summary: HTTP queries logger with flexible filters and ip block manager.
Home-page: https://github.com/HosseinSayyedMousavi
Author: Hossein SayyedMousavi
Author-email: hossein.sayyedmousavi@gmail.com
License: MIT License
Keywords: django,database,user,activity log
Classifier: Framework :: Django
Classifier: Development Status :: 4 - Beta
Classifier: Environment :: Web Environment
Classifier: Intended Audience :: Developers
Classifier: License :: OSI Approved :: MIT License
Classifier: Programming Language :: Python
Classifier: Programming Language :: Python :: 2
Classifier: Programming Language :: Python :: 2.6
Classifier: Programming Language :: Python :: 2.7
Classifier: Programming Language :: Python :: 3.8
Classifier: Programming Language :: Python :: 3.11
Classifier: Topic :: Software Development :: Libraries :: Python Modules
License-File: LICENSE
Requires-Dist: django <5.0.0
Requires-Dist: pprintpp <1.0.0
